IncrementRegister.v
/*
 CS 274
 Ursinus College

 @author: Mia Sideris
 @purpose: Demonstrate the implementation of Read-Only Increment Registers: Instruction Count, Memory Access and Memory Correction
 */

module IncrementRegister(
    input clk,
    input reset,
    input Instruc_Count_Ex,
    input MEM_Acc_Ex,
    input MEM_Correct_Ex,

    output reg [19:0] Instruc_Reg,
    output reg [19:0] MEM_Acc_Reg,
    output reg [19:0] MEM_Correct_Reg
);

always @ (posedge clk or posedge reset) begin
    if(reset)
    begin
        Instruc_Reg<= 20'b0;
        MEM_Acc_Reg<= 20'b0;
        MEM_Correct_Reg<=20'b0;
    end
end

always @ (posedge clk)begin
    if(reset)
    begin
        Instruc_Reg<= 20'b0;
        MEM_Acc_Reg<= 20'b0;
        MEM_Correct_Reg<=20'b0;
    end
    else
    begin
    if(Instruc_Count_Ex)
        Instruc_Reg = Instruc_Reg +1;
    if(MEM_Acc_Ex)
        MEM_Acc_Reg = MEM_Acc_Reg +1;
    if(MEM_Correct_Ex)
        MEM_Correct_Reg = MEM_Correct_Reg +1;
    end
end

endmodule

ALU/arithmetic/INC/IncrementRegister_tb.v
/*
 CS 274
 Ursinus College

 @author: Mia Sideris
 @purpose: Demonstrate the implementation of Read-Only Increment Registers: Instruction Count, Memory Access and Memory Correction
 */

`timescale 1ns/1ns

module IncrementRegister_tb;

    parameter CLK_Period = 10;

    reg clk;
    reg reset;
    reg Instruc_Count_Ex;
    reg MEM_Acc_Ex;
    reg MEM_Correct_Ex;

    wire [19:0] Instruc_Reg;
    wire [19:0] MEM_Acc_Reg;
    wire [19:0] MEM_Correct_Reg;

    IncrementRegister DUT(
        .clk(clk),
        .reset(reset),
        .Instruc_Count_Ex(Instruc_Count_Ex),
        .MEM_Acc_Ex(MEM_Acc_Ex),
        .MEM_Correct_Ex(MEM_Correct_Ex),
        .Instruc_Reg(Instruc_Reg),
        .MEM_Acc_Reg(MEM_Acc_Reg),
        .MEM_Correct_Reg(MEM_Correct_Reg)
    );

    always #((CLK_Period/2)) clk = ~clk;

    initial begin
        $dumpfile("IncrementRegister_tb.vcd");
        $dumpvars(0, IncrementRegister_tb);
        clk = 0;
        reset=1;
        Instruc_Count_Ex=1;
        MEM_Acc_Ex=1;
        MEM_Correct_Ex=0;

        #50;

        reset=0;
        #10
        Instruc_Count_Ex=1;
        #10
        Instruc_Count_Ex=1;
        #10
        MEM_Acc_Ex=1;
        #10
        MEM_Correct_Ex=1;
        #50;
        $finish;
    end
endmodule

ALU/arithmetic/INC/IncrementRegister_tb.vcd
$date
	Fri Mar 22 11:27:34 2024
$end
$version
	Icarus Verilog
$end
$timescale
	1ns
$end
$scope module IncrementRegister_tb $end
$var wire 20 ! MEM_Correct_Reg [19:0] $end
$var wire 20 " MEM_Acc_Reg [19:0] $end
$var wire 20 # Instruc_Reg [19:0] $end
$var parameter 32 $ CLK_Period $end
$var reg 1 % Instruc_Count_Ex $end
$var reg 1 & MEM_Acc_Ex $end
$var reg 1 ' MEM_Correct_Ex $end
$var reg 1 ( clk $end
$var reg 1 ) reset $end
$scope module DUT $end
$var wire 1 % Instruc_Count_Ex $end
$var wire 1 & MEM_Acc_Ex $end
$var wire 1 ' MEM_Correct_Ex $end
$var wire 1 ( clk $end
$var wire 1 ) reset $end
$var reg 20 * Instruc_Reg [19:0] $end
$var reg 20 + MEM_Acc_Reg [19:0] $end
$var reg 20 , MEM_Correct_Reg [19:0] $end
$upscope $end
$upscope $end
$enddefinitions $end
$comment Show the parameter values. $end
$dumpall
b1010 $
$end
#0
$dumpvars
b0 ,
b0 +
b0 *
1)
0(
0'
1&
1%
b0 #
b0 "
b0 !
$end
#5
1(
#10
0(
#15
1(
#20
0(
#25
1(
#30
0(
#35
1(
#40
0(
#45
1(
#50
0(
0)
#55
b1 "
b1 +
b1 #
b1 *
1(
#60
0(
#65
b10 "
b10 +
b10 #
b10 *
1(
#70
0(
#75
b11 "
b11 +
b11 #
b11 *
1(
#80
0(
#85
b100 "
b100 +
b100 #
b100 *
1(
#90
0(
1'
#95
b1 !
b1 ,
b101 "
b101 +
b101 #
b101 *
1(
#100
0(
#105
b10 !
b10 ,
b110 "
b110 +
b110 #
b110 *
1(
#110
0(
#115
b11 !
b11 ,
b111 "
b111 +
b111 #
b111 *
1(
#120
0(
#125
b100 !
b100 ,
b1000 "
b1000 +
b1000 #
b1000 *
1(
#130
0(
#135
b101 !
b101 ,
b1001 "
b1001 +
b1001 #
b1001 *
1(
