ALU/logic/xor/xor.v
module xor_word (
   input [19:0] a,
   input [19:0] b,
   output reg [19:0] c,
   output reg zero
);

   integer i;

   always @(a or b) begin
      for (i = 0; i < 20; i++) begin
         c[i] = a[i] ^ b[i];
      end
    
      zero = !(|c);
   end  

endmodule

ALU/logic/xor/testbench_xor.v
`include "xor.v"
`default_nettype none


module testbench_xor;
    // Set inputs and outputs
    reg [19:0] a;
    reg [19:0] b;
    wire [19:0] c;
    wire zero;

    integer i;
    integer MAX_ITERS = 10;
    integer SEED = 10531;

    // Instantiate the XOR
    xor_word x0 (
        .a (a),
        .b (b),
        .c (c),
        .zero (zero)
    );

    initial begin
        a <= 0;
        b <= 0;

        $dumpfile("testbench_xor.vcd");
        $dumpvars(1,x0);
        $monitor ("a: 0b%0b - b: 0b%0b - c: 0b%0b - zero: 0b%0b", a, b, c, zero);

        for (i = 0; i < MAX_ITERS; i++) begin
            #10 a <= $urandom(SEED);
                b <= $urandom(SEED);
        end
    end

endmodule

ALU/logic/xor/testbench_xor.vcd
$date
	Wed Feb 21 11:53:28 2024
$end
$version
	Icarus Verilog
$end
$timescale
	1s
$end
$scope module testbench_xor $end
$scope module x0 $end
$var wire 20 ! a [19:0] $end
$var wire 20 " b [19:0] $end
$var reg 20 # c [19:0] $end
$var reg 1 $ zero $end
$var integer 32 % i [31:0] $end
$upscope $end
$upscope $end
$enddefinitions $end
$comment Show the parameter values. $end
$dumpall
$end
#0
$dumpvars
b10100 %
1$
b0 #
b0 "
b0 !
$end
#10
0$
b11110111001001000000 #
b10100 %
b1011100100000010110 "
b10101011101001010110 !
#20
b1100000010111110000 #
b10100 %
b10100011110000111010 "
b11000011100111001010 !
#30
b10111011101100100000 #
b10100 %
b11011110100110100 "
b10100000011000010100 !
#40
b10111010001011101001 #
b10100 %
b11101101111011001 "
b10100111100100110000 !
#50
b10010111000010001111 #
b10100 %
b11111110010111101010 "
b1101001010101100101 !
#60
b101010111011100111 #
b10100 %
b11100100010100000111 "
b11001110101111100000 !
#70
b1111010110011100111 #
b10100 %
b1101111011100011 "
b1110111001000000100 !
#80
b11000000010001110111 #
b10100 %
b111001010000111 "
b11000111011011110000 !
#90
b1110110100001001110 #
b10100 %
b1010000001001000100 "
b100110101000001010 !
#100
b11110101110001000 #
b10100 %
b11110010010010011010 "
b11101100111100010010 !
